app/.editorconfig
app/.eslintignore
app/.eslintrc.cjs
app/.gitignore
app/.npmrc
app/.prettierignore
app/.prettierrc.json
app/.prettierrc.yaml
app/README.md
app/README_ZH.md
app/app-static.py
app/app.py
app/dev-app-update.yml
app/electron-builder.yml
app/electron.vite.config.ts
app/package-lock.json
app/package.json
app/pnpm-lock.yaml
app/postcss.config.js
app/tailwind.config.js
app/test.py
app/tsconfig.json
app/tsconfig.node.json
app/tsconfig.web.json
app/resources/icon.png
app/resources/logo.svg
app/src/main/index.ts
app/src/preload/index.d.ts
app/src/preload/index.ts
app/src/renderer/index.html
app/src/renderer/src/App.tsx
app/src/renderer/src/env.d.ts
app/src/renderer/src/main.tsx
app/src/renderer/src/typing.ts
app/src/renderer/src/assets/base.css
app/src/renderer/src/assets/electron.svg
app/src/renderer/src/assets/iconfont.js
app/src/renderer/src/assets/main.css
app/src/renderer/src/assets/wavy-lines.svg
app/src/renderer/src/assets/svg/empty.svg
app/src/renderer/src/components/Versions.tsx
app/src/renderer/src/components/detail-table.tsx
app/src/renderer/src/components/ellipsis-text.tsx
app/src/renderer/src/components/empty.tsx
app/src/renderer/src/components/file-structure-table.tsx
app/src/renderer/src/components/icon-font.tsx
app/src/renderer/src/components/readFileDir.tsx
app/src/renderer/src/components/HightLightText/index.module.scss
app/src/renderer/src/components/HightLightText/index.tsx
app/src/renderer/src/components/detail-card/index.tsx
app/src/renderer/src/components/filter-cascader/index.module.scss
app/src/renderer/src/components/filter-cascader/index.tsx
app/src/renderer/src/components/text-tooltip/index.module.scss
app/src/renderer/src/components/text-tooltip/index.tsx
app/src/renderer/src/constant/Language.ts
app/src/renderer/src/constant/index.ts
app/src/renderer/src/constant/storage.ts
app/src/renderer/src/locale/en.ts
app/src/renderer/src/locale/zh.ts
app/src/renderer/src/pages/index.module.scss
app/src/renderer/src/pages/index.tsx
dingo_python-2.0.0.dist-info/licenses/LICENSE
dingo_python-2.0.0.dist-info/METADATA
dingo_python-2.0.0.dist-info/WHEEL
dingo_python-2.0.0.dist-info/top_level.txt
dingo_python-2.0.0.dist-info/RECORD
