Metadata-Version: 2.4
Name: dingo-python
Version: 2.0.0
Summary: A Comprehensive AI Data Quality Evaluation Tool for Large Models
Home-page: https://github.com/MigoXLab/dingo
Author: Dingo
Classifier: Programming Language :: Python :: 3
Classifier: Operating System :: OS Independent
Requires-Python: >=3.10
License-File: LICENSE
Requires-Dist: boto3==1.28.43
Requires-Dist: botocore==1.31.43
Requires-Dist: chardet
Requires-Dist: datasets
Requires-Dist: fasttext-wheel==0.9.2
Requires-Dist: hanziconv
Requires-Dist: httpx
Requires-Dist: huggingface_hub
Requires-Dist: jieba
Requires-Dist: jsonlines
Requires-Dist: langid
Requires-Dist: openai>=1.56.2
Requires-Dist: opencv-python
Requires-Dist: packaging>=24.1
Requires-Dist: pandas
Requires-Dist: Pillow>=9.4.0
Requires-Dist: prettytable
Requires-Dist: pyahocorasick
Requires-Dist: nltk
Requires-Dist: numpy>=1.26.4
Requires-Dist: pydantic
Requires-Dist: requests
Requires-Dist: textstat
Requires-Dist: toml
Requires-Dist: transformers
Requires-Dist: wordninja==2.0.0
Requires-Dist: zhon
Requires-Dist: fastmcp>=2.0.0
Requires-Dist: twine==6.0.1
Requires-Dist: pkginfo==1.12.0
Requires-Dist: diff_match_patch
Requires-Dist: sqlalchemy
Requires-Dist: openpyxl
Requires-Dist: xlrd
Requires-Dist: xlwt
Requires-Dist: pytest
Requires-Dist: pyarrow
Requires-Dist: fastapi
Requires-Dist: uvicorn
Provides-Extra: agent
Requires-Dist: langchain>=1.0.0; extra == "agent"
Requires-Dist: langchain-openai>=1.0.0; extra == "agent"
Requires-Dist: tavily-python>=0.3.0; extra == "agent"
Provides-Extra: all
Requires-Dist: langchain>=1.0.0; extra == "all"
Requires-Dist: langchain-openai>=1.0.0; extra == "all"
Requires-Dist: tavily-python>=0.3.0; extra == "all"
Dynamic: author
Dynamic: classifier
Dynamic: description
Dynamic: description-content-type
Dynamic: home-page
Dynamic: license-file
Dynamic: provides-extra
Dynamic: requires-dist
Dynamic: requires-python
Dynamic: summary
